main.py
cvg_core/__init__.py
cvg_core/proper_procedures.py
cvg_core/objects/__init__.py
cvg_core/objects/crypto_object/__init__.py
cvg_core/objects/crypto_object/ecdh_object.py
cvg_core/objects/network_object/__init__.py
cvg_core/objects/network_object/connection_object.py
cvg_core/objects/network_object/packet_object.py
cvg_core/procedures/__init__.py
cvg_core/procedures/command_send_and_receive.py
cvg_core/procedures/crypto_send_and_receive.py
cvg_core/procedures/establish_connection.py
cvg_core/procedures/send_and_receive.py
cvg_core-0.1.3.dist-info/METADATA
cvg_core-0.1.3.dist-info/WHEEL
cvg_core-0.1.3.dist-info/top_level.txt
cvg_core-0.1.3.dist-info/RECORD
