Metadata-Version: 2.1
Name: cvg-core
Version: 0.1.3
Summary: A network protocol dependancy. Objects & Procedures.
Author: t-nician
Project-URL: Homepage, https://github.com/t-nician/cvg-core
Project-URL: Issues, https://github.com/t-nician/cvg-core/issues
Requires-Python: >=3.10
Requires-Dist: pycryptodome
Requires-Dist: cryptography
